{"container_type": "Author", "filled": ["basics", "publications", "indices", "counts"], "scholar_id": "9A9B_u0AAAAJ", "source": "AUTHOR_PROFILE_PAGE", "name": "fei teng", "url_picture": "https://scholar.googleusercontent.com/citations?view_op=view_photo&user=9A9B_u0AAAAJ&citpid=1", "affiliation": "Hunan University", "organization": 12440888459854724508, "interests": [], "email_domain": "@hnu.edu.cn", "citedby": 31, "publications": {"9A9B_u0AAAAJ:zYLM7Y9cAGgC": {"container_type": "Publication", "source": "AUTHOR_PUBLICATION_ENTRY", "bib": {"title": "Unveiling the potential of segment anything model 2 for rgb-thermal semantic segmentation with language guidance", "pub_year": "2025"}, "filled": false, "author_pub_id": "9A9B_u0AAAAJ:zYLM7Y9cAGgC", "num_citations": 9, "citedby_url": "https://scholar.google.com/scholar?oi=bibs&hl=en&cites=14956751058670592786", "cites_id": ["14956751058670592786"]}, "9A9B_u0AAAAJ:Tyk-4Ss8FVUC": {"container_type": "Publication", "source": "AUTHOR_PUBLICATION_ENTRY", "bib": {"title": "Omnidirectional Multi-Object Tracking", "pub_year": "2025"}, "filled": false, "author_pub_id": "9A9B_u0AAAAJ:Tyk-4Ss8FVUC", "num_citations": 8, "citedby_url": "https://scholar.google.com/scholar?oi=bibs&hl=en&cites=6830651285155374559", "cites_id": ["6830651285155374559"]}, "9A9B_u0AAAAJ:9yKSN-GCB0IC": {"container_type": "Publication", "source": "AUTHOR_PUBLICATION_ENTRY", "bib": {"title": "OAFuser: Towards omni-aperture fusion for light field semantic segmentation", "pub_year": "2024"}, "filled": false, "author_pub_id": "9A9B_u0AAAAJ:9yKSN-GCB0IC", "num_citations": 8, "citedby_url": "https://scholar.google.com/scholar?oi=bibs&hl=en&cites=609900843882242493", "cites_id": ["609900843882242493"]}, "9A9B_u0AAAAJ:qjMakFHDy7sC": {"container_type": "Publication", "source": "AUTHOR_PUBLICATION_ENTRY", "bib": {"title": "LF tracy: A unified single-pipeline approach for salient object detection in light field cameras", "pub_year": "2024"}, "filled": false, "author_pub_id": "9A9B_u0AAAAJ:qjMakFHDy7sC", "num_citations": 6, "citedby_url": "https://scholar.google.com/scholar?oi=bibs&hl=en&cites=12243310799251487115", "cites_id": ["12243310799251487115"]}, "9A9B_u0AAAAJ:roLk4NBRz8UC": {"container_type": "Publication", "source": "AUTHOR_PUBLICATION_ENTRY", "bib": {"title": "OmniTrack++: Omnidirectional Multi-Object Tracking by Learning Large-FoV Trajectory Feedback", "pub_year": "2025"}, "filled": false, "author_pub_id": "9A9B_u0AAAAJ:roLk4NBRz8UC", "num_citations": 0}, "9A9B_u0AAAAJ:LkGwnXOMwfcC": {"container_type": "Publication", "source": "AUTHOR_PUBLICATION_ENTRY", "bib": {"title": "DepTR-MOT: Unveiling the Potential of Depth-Informed Trajectory Refinement for Multi-Object Tracking", "pub_year": "2025"}, "filled": false, "author_pub_id": "9A9B_u0AAAAJ:LkGwnXOMwfcC", "num_citations": 0}, "9A9B_u0AAAAJ:_FxGoFyzp5QC": {"container_type": "Publication", "source": "AUTHOR_PUBLICATION_ENTRY", "bib": {"title": "Visually Grounded Narratives: Reducing Cognitive Burden in Researcher-Participant Interaction", "pub_year": "2025"}, "filled": false, "author_pub_id": "9A9B_u0AAAAJ:_FxGoFyzp5QC", "num_citations": 0}, "9A9B_u0AAAAJ:WF5omc3nYNoC": {"container_type": "Publication", "source": "AUTHOR_PUBLICATION_ENTRY", "bib": {"title": "QuaDreamer: Controllable Panoramic Video Generation for Quadruped Robots", "pub_year": "2025"}, "filled": false, "author_pub_id": "9A9B_u0AAAAJ:WF5omc3nYNoC", "num_citations": 0}, "9A9B_u0AAAAJ:ufrVoPGSRksC": {"container_type": "Publication", "source": "AUTHOR_PUBLICATION_ENTRY", "bib": {"title": "Hallucinating 360 {\\deg}: Panoramic Street-View Generation via Local Scenes Diffusion and Probabilistic Prompting", "pub_year": "2025"}, "filled": false, "author_pub_id": "9A9B_u0AAAAJ:ufrVoPGSRksC", "num_citations": 0}, "9A9B_u0AAAAJ:Se3iqnhoufwC": {"container_type": "Publication", "source": "AUTHOR_PUBLICATION_ENTRY", "bib": {"title": "NRSeg: Noise-Resilient Learning for BEV Semantic Segmentation via Driving World Models", "pub_year": "2025"}, "filled": false, "author_pub_id": "9A9B_u0AAAAJ:Se3iqnhoufwC", "num_citations": 0}, "9A9B_u0AAAAJ:eQOLeE2rZwMC": {"container_type": "Publication", "source": "AUTHOR_PUBLICATION_ENTRY", "bib": {"title": "Out-of-Distribution Semantic Occupancy Prediction", "pub_year": "2025"}, "filled": false, "author_pub_id": "9A9B_u0AAAAJ:eQOLeE2rZwMC", "num_citations": 0}, "9A9B_u0AAAAJ:YsMSGLbcyi4C": {"container_type": "Publication", "source": "AUTHOR_PUBLICATION_ENTRY", "bib": {"title": "Go Beyond Earth: Understanding Human Actions and Scenes in Microgravity Environments", "pub_year": "2025"}, "filled": false, "author_pub_id": "9A9B_u0AAAAJ:YsMSGLbcyi4C", "num_citations": 0}, "9A9B_u0AAAAJ:Y0pCki6q_DkC": {"container_type": "Publication", "source": "AUTHOR_PUBLICATION_ENTRY", "bib": {"title": "Panoramic Out-of-Distribution Segmentation", "pub_year": "2025"}, "filled": false, "author_pub_id": "9A9B_u0AAAAJ:Y0pCki6q_DkC", "num_citations": 0}, "9A9B_u0AAAAJ:IjCSPb-OGe4C": {"container_type": "Publication", "source": "AUTHOR_PUBLICATION_ENTRY", "bib": {"title": "Unifying Light Field Perception with Field of Parallax", "pub_year": "2025"}, "filled": false, "author_pub_id": "9A9B_u0AAAAJ:IjCSPb-OGe4C", "num_citations": 0}, "9A9B_u0AAAAJ:UeHWp8X0CEIC": {"container_type": "Publication", "source": "AUTHOR_PUBLICATION_ENTRY", "bib": {"title": "LF Tracy: A Unified Single-Pipeline Paradigm for Salient Object Detection in Light Field Cameras", "pub_year": "2024"}, "filled": false, "author_pub_id": "9A9B_u0AAAAJ:UeHWp8X0CEIC", "num_citations": 0}, "9A9B_u0AAAAJ:W7OEmFMy1HYC": {"container_type": "Publication", "source": "AUTHOR_PUBLICATION_ENTRY", "bib": {"title": "Supplementary Materials for Omnidirectional Multi-Object Tracking"}, "filled": false, "author_pub_id": "9A9B_u0AAAAJ:W7OEmFMy1HYC", "num_citations": 0}}, "citedby5y": 31, "hindex": 4, "hindex5y": 4, "i10index": 0, "i10index5y": 0, "cites_per_year": {"2023": 1, "2024": 5, "2025": 25}, "updated": "2025-12-03 08:37:58.425100"}